CHANGELOG.md
LICENSE
README.md
setup.cfg
setup.py
docs/CONTRIBUTING.md
docs/README-API.md
docs/logdissect.1
docs/logdissect.3
logdissect/__init__.py
logdissect/core.py
logdissect/utils.py
logdissect.egg-info/PKG-INFO
logdissect.egg-info/SOURCES.txt
logdissect.egg-info/dependency_links.txt
logdissect.egg-info/entry_points.txt
logdissect.egg-info/top_level.txt
logdissect/filters/__init__.py
logdissect/filters/blank.py
logdissect/filters/dhost.py
logdissect/filters/grep.py
logdissect/filters/last.py
logdissect/filters/process.py
logdissect/filters/protocol.py
logdissect/filters/range.py
logdissect/filters/rdhost.py
logdissect/filters/rgrep.py
logdissect/filters/rprocess.py
logdissect/filters/rprotocol.py
logdissect/filters/rshost.py
logdissect/filters/rsource.py
logdissect/filters/shost.py
logdissect/filters/source.py
logdissect/filters/type.py
logdissect/output/__init__.py
logdissect/output/blank.py
logdissect/output/linejson.py
logdissect/output/log.py
logdissect/output/sojson.py
logdissect/output/type.py
logdissect/parsers/__init__.py
logdissect/parsers/blank.py
logdissect/parsers/ciscoios.py
logdissect/parsers/linejson.py
logdissect/parsers/sojson.py
logdissect/parsers/syslog.py
logdissect/parsers/syslogiso.py
logdissect/parsers/syslognohost.py
logdissect/parsers/tcpdump.py
logdissect/parsers/type.py
logdissect/parsers/webaccess.py
logdissect/parsers/windowsrsyslog.py