Metadata-Version: 1.1
Name: logdissect
Version: 3.0.1
Summary: Robust CLI syslog forensics tool
Home-page: https://github.com/dogoncouch/logdissect
Author: Dan Persons
Author-email: dpersonsdev@gmail.com
License: UNKNOWN
Download-URL: https://github.com/dogoncouch/logdissect/archive/v3.0.1.tar.gz
Keywords: log,syslog,analysis,forensics,security,cli,secops,data-science,forensic-analysis,log-analysis,log-analyzer,log-viewer,log-parser,log-viewer,log-parsing,python-library,python-module,parser,data-analysis,library,module
Platform: UNKNOWN
Classifier: Development Status :: 5 - Production/Stable
Classifier: Environment :: Console
Classifier: Intended Audience :: System Administrators
Classifier: Intended Audience :: Science/Research
Classifier: License :: OSI Approved :: MIT License
Classifier: Natural Language :: English
Classifier: Operating System :: POSIX
Classifier: Programming Language :: Python
Classifier: Topic :: System :: Systems Administration
Classifier: Topic :: Scientific/Engineering :: Information Analysis
Classifier: Topic :: Security
Classifier: Topic :: System :: Logging
